{
  "questions": [
    {
      "question": "Яка столиця Франції?",
      "answers": ["Лондон", "Мадрид", "Париж"],
      "correctAnswer": "Париж"
    },
    {
      "question": "Скільки планет у Сонячній системі?",
      "answers": ["5", "8", "9"],
      "correctAnswer": "8"
    },
    {
      "question": "Яка кольорова модель RGB?",
      "answers": ["Red, Green, Black", "Red, Green, Blue", "Red, Gray, Blue"],
      "correctAnswer": "Red, Green, Blue"
    },
    {
      "question": "Яка найбільша планета у Сонячній системі?",
      "answers": ["Земля", "Марс", "Юпітер"],
      "correctAnswer": "Юпітер"
    },
    {
      "question": "Що вимірює термометр?",
      "answers": ["Тиск", "Температуру", "Швидкість"],
      "correctAnswer": "Температуру"
    },
    {
      "question": "Скільки років триває один природний рік на Землі?",
      "answers": ["365", "366", "364"],
      "correctAnswer": "365"
    },
    {
      "question": "Як називається найбільше океан у світі?",
      "answers": ["Атлантичний", "Тихий", "Індійський"],
      "correctAnswer": "Тихий"
    },
    {
      "question": "Яка найвища гора на Землі?",
      "answers": ["Кіліманджаро", "Ельбрус", "Еверест"],
      "correctAnswer": "Еверест"
    },
    {
      "question": "Як називається найбільший супутник Землі?",
      "answers": ["Місяць", "Марс", "Титан"],
      "correctAnswer": "Місяць"
    },
    {
      "question": "Яка хімічна формула води?",
      "answers": ["H2O2", "HO2", "H2O"],
      "correctAnswer": "H2O"
    },
    {
      "question": "Скільки континентів на Землі?",
      "answers": ["3", "5", "7"],
      "correctAnswer": "7"
    },
    {
      "question": "Яка столиця Японії?",
      "answers": ["Пекін", "Сеул", "Токіо"],
      "correctAnswer": "Токіо"
    },
    {
      "question": "Яка найбільша пустеля у світі?",
      "answers": ["Сахара", "Гобі", "Атакама"],
      "correctAnswer": "Сахара"
    },
    {
      "question": "Яка ріка найдовша на Землі?",
      "answers": ["Ніл", "Амазонка", "Янцзи"],
      "correctAnswer": "Амазонка"
    },
    {
      "question": "Який газ є основним компонентом атмосфери Землі?",
      "answers": ["Оксиген", "Вуглекислий газ", "Азот"],
      "correctAnswer": "Азот"
    }
  ]
}
